depforge/__init__.py
depforge-0.1.0.dist-info/METADATA
depforge-0.1.0.dist-info/WHEEL
depforge-0.1.0.dist-info/RECORD
