Metadata-Version: 2.4
Name: depforge
Version: 0.1.0
Summary: Find breaking changes in your Python dependencies
Project-URL: Homepage, https://github.com/fswair/depforge
Project-URL: Repository, https://github.com/fswair/depforge
Author-email: Mert <contact@tomris.dev>
License-Expression: MIT
Keywords: breaking-changes,changelog,cli,dependencies,outdated
Classifier: Development Status :: 3 - Alpha
Classifier: Environment :: Console
Classifier: Intended Audience :: Developers
Classifier: License :: OSI Approved :: MIT License
Classifier: Programming Language :: Python :: 3
Classifier: Programming Language :: Python :: 3.10
Classifier: Programming Language :: Python :: 3.11
Classifier: Programming Language :: Python :: 3.12
Classifier: Topic :: Software Development :: Libraries :: Python Modules
Requires-Python: >=3.10
